cattleprod/__init__.py
cattleprod/__main__.py
cattleprod-0.6.0.dist-info/DESCRIPTION.rst
cattleprod-0.6.0.dist-info/METADATA
cattleprod-0.6.0.dist-info/RECORD
cattleprod-0.6.0.dist-info/WHEEL
cattleprod-0.6.0.dist-info/metadata.json
cattleprod-0.6.0.dist-info/top_level.txt
tests/__init__.py
tests/configdata.py
tests/testbasic.py
