Metadata-Version: 2.0
Name: cattleprod
Version: 0.6.0
Summary: A quickly constructed interface to the Rancher API (http://rancher.com)
Home-page: https://github.com/flypenguin/python-cattleprod
Author: Axel Bock
Author-email: mr.axel.bock@gmail.com
License: UNKNOWN
Download-URL: https://github.com/flypenguin/python-cattleprod/tarball/0.6.0
Keywords: rancher,api
Platform: UNKNOWN
Classifier: License :: OSI Approved :: MIT License
Classifier: Development Status :: 4 - Beta
Classifier: Intended Audience :: Developers
Classifier: Intended Audience :: System Administrators
Classifier: Programming Language :: Python :: 2
Classifier: Programming Language :: Python :: 3
Classifier: Operating System :: POSIX
Classifier: Operating System :: MacOS
Classifier: Topic :: System :: Systems Administration
Requires-Dist: dotmap
Requires-Dist: requests
